{
    "affected": [
        {
            "package": {
                "ecosystem": "FreeBSD:ports",
                "name": "silc-irssi-client"
            },
            "ranges": [
                {
                    "events": [
                        {
                            "fixed": "1.1.4"
                        },
                        {
                            "introduced": "0"
                        }
                    ],
                    "type": "ECOSYSTEM"
                }
            ]
        },
        {
            "package": {
                "ecosystem": "FreeBSD:ports",
                "name": "silc-client"
            },
            "ranges": [
                {
                    "events": [
                        {
                            "fixed": "1.1.4"
                        },
                        {
                            "introduced": "0"
                        }
                    ],
                    "type": "ECOSYSTEM"
                }
            ]
        },
        {
            "package": {
                "ecosystem": "FreeBSD:ports",
                "name": "silc-server"
            },
            "ranges": [
                {
                    "events": [
                        {
                            "fixed": "1.1.2"
                        },
                        {
                            "introduced": "0"
                        }
                    ],
                    "type": "ECOSYSTEM"
                }
            ]
        }
    ],
    "database_specific": {
        "cite": [
            "http://www.coresecurity.com/?action=item&id=2206"
        ],
        "discovery": "2008-03-25T00:00:00Z",
        "references": {
            "bid": [
                "28373"
            ]
        },
        "vid": "ff304c35-fb5b-11dc-91c1-00e0815b8da8"
    },
    "details": "Core Security Technologies reports:\n\n> A remote buffer overflow vulnerability found in a library used by both\n> the SILC server and client to process packets containing cryptographic\n> material may allow an un-authenticated client to executearbitrary code\n> on the server with the privileges of the user account running the\n> server, or a malicious SILC server to compromise client systems and\n> execute arbitrary code with the privileges of the user account running\n> the SILC client program.\n",
    "id": "FreeBSD-2008-0032",
    "modified": "2008-03-26T00:00:00Z",
    "published": "2008-03-26T00:00:00Z",
    "references": [
        {
            "type": "REPORT",
            "url": "http://www.coresecurity.com/?action=item&id=2206"
        },
        {
            "type": "ADVISORY",
            "url": "https://www.securityfocus.com/bid/28373/info"
        },
        {
            "type": "WEB",
            "url": "http://www.coresecurity.com/?action=item&id=2206"
        }
    ],
    "schema_version": "1.7.0",
    "summary": "silc -- pkcs_decode buffer overflow"
}
