{
    "affected": [
        {
            "package": {
                "ecosystem": "FreeBSD:ports",
                "name": "linux-opera"
            },
            "ranges": [
                {
                    "events": [
                        {
                            "fixed": "8.02"
                        },
                        {
                            "introduced": "0"
                        }
                    ],
                    "type": "ECOSYSTEM"
                }
            ]
        },
        {
            "package": {
                "ecosystem": "FreeBSD:ports",
                "name": "opera-devel"
            },
            "ranges": [
                {
                    "events": [
                        {
                            "fixed": "8.02"
                        },
                        {
                            "introduced": "0"
                        }
                    ],
                    "type": "ECOSYSTEM"
                }
            ]
        },
        {
            "package": {
                "ecosystem": "FreeBSD:ports",
                "name": "opera"
            },
            "ranges": [
                {
                    "events": [
                        {
                            "fixed": "8.02"
                        },
                        {
                            "introduced": "0"
                        }
                    ],
                    "type": "ECOSYSTEM"
                }
            ]
        }
    ],
    "database_specific": {
        "discovery": "2005-07-28T00:00:00Z",
        "vid": "934b1de4-00d7-11da-bc08-0001020eed82"
    },
    "details": "A Secunia Advisory reports:\n\n> Secunia Research has discovered a vulnerability in Opera,\n> which can be exploited by malicious people to conduct\n> cross-site scripting attacks and retrieve a user's\n> files.\n>\n> The vulnerability is caused due to Opera allowing a user\n> to drag e.g. an image, which is actually a \"javascript:\"\n> URI, resulting in cross-site scripting if dropped over\n> another site. This may also be used to populate a file\n> upload form, resulting in uploading of arbitrary files to\n> a malicious web site.\n>\n> Successful exploitation requires that the user is tricked\n> into dragging and dropping e.g. an image or a link.",
    "id": "FreeBSD-kernel-2005-0098",
    "modified": "2006-06-08T00:00:00Z",
    "published": "2005-07-30T00:00:00Z",
    "references": [
        {
            "type": "WEB",
            "url": "http://secunia.com/advisories/15756/"
        },
        {
            "type": "WEB",
            "url": "http://www.opera.com/freebsd/changelogs/802/"
        }
    ],
    "schema_version": "1.7.0",
    "summary": "opera -- image dragging vulnerability"
}
