{
    "affected": [
        {
            "package": {
                "ecosystem": "FreeBSD:ports",
                "name": "flyspray"
            },
            "ranges": [
                {
                    "events": [
                        {
                            "fixed": "0.9.8"
                        },
                        {
                            "introduced": "0"
                        }
                    ],
                    "type": "ECOSYSTEM"
                }
            ]
        }
    ],
    "database_specific": {
        "cite": [
            "http://secunia.com/advisories/17316/"
        ],
        "discovery": "2005-10-26T00:00:00Z",
        "references": {
            "bid": [
                "15209"
            ]
        },
        "vid": "f4b95430-51d8-11da-8e93-0010dc4afb40"
    },
    "details": "A Secunia Advisory reports:\n\n> Lostmon has reported some vulnerabilities in Flyspray, which can be\n> exploited by malicious people to conduct cross-site scripting attacks.\n>\n> Some input isn\\'t properly sanitised before being returned to the\n> user. This can be exploited to execute arbitrary HTML and script code\n> in a user\\'s browser session in context of an affected site.\n",
    "id": "FreeBSD-2005-0304",
    "modified": "2005-11-29T00:00:00Z",
    "published": "2005-11-10T00:00:00Z",
    "references": [
        {
            "type": "REPORT",
            "url": "http://secunia.com/advisories/17316/"
        },
        {
            "type": "ADVISORY",
            "url": "https://www.securityfocus.com/bid/15209/info"
        },
        {
            "type": "WEB",
            "url": "http://secunia.com/advisories/17316/"
        },
        {
            "type": "WEB",
            "url": "http://lostmon.blogspot.com/2005/10/flyspray-bug-killer-multiple-variable.html"
        }
    ],
    "schema_version": "1.7.0",
    "summary": "flyspray -- cross-site scripting vulnerabilities"
}
