{
    "affected": [
        {
            "package": {
                "ecosystem": "FreeBSD:ports",
                "name": "py-django-cms"
            },
            "ranges": [
                {
                    "events": [
                        {
                            "fixed": "2.3.5"
                        },
                        {
                            "introduced": "0"
                        }
                    ],
                    "type": "ECOSYSTEM"
                }
            ]
        }
    ],
    "database_specific": {
        "cite": [
            "https://www.django-cms.org/en/blog/2012/12/04/2-3-5-security-release/"
        ],
        "discovery": "2012-12-04T00:00:00Z",
        "vid": "3886cafe-668c-11e2-94b8-1c4bd681f0cf"
    },
    "details": "Cross-site scripting (XSS) vulnerability\n\n> Jonas Obrist reports: The security issue allows users with limited\n> admin access to elevate their privileges through XSS injection using\n> the page_attribute template tag. Only users with admin access and the\n> permission to edit at least one django CMS page object could exploit\n> this vulnerability. Websites that do not use the page_attribute\n> template tag are not affected.\n",
    "id": "FreeBSD-2013-0014",
    "modified": "2013-01-25T00:00:00Z",
    "published": "2013-01-25T00:00:00Z",
    "references": [
        {
            "type": "REPORT",
            "url": "https://www.django-cms.org/en/blog/2012/12/04/2-3-5-security-release/"
        },
        {
            "type": "WEB",
            "url": "https://www.django-cms.org/en/blog/2012/12/04/2-3-5-security-release/"
        }
    ],
    "schema_version": "1.7.0",
    "summary": "django-cms -- XSS Vulnerability"
}
