{
    "affected": [
        {
            "package": {
                "ecosystem": "FreeBSD:ports",
                "name": "znc"
            },
            "ranges": [
                {
                    "events": [
                        {
                            "fixed": "1.0_1"
                        },
                        {
                            "introduced": "0"
                        }
                    ],
                    "type": "ECOSYSTEM"
                }
            ]
        }
    ],
    "database_specific": {
        "cite": [
            "https://github.com/znc/znc/commit/2bd410ee5570cea127233f1133ea22f25174eb28"
        ],
        "discovery": "2013-05-27T00:00:00Z",
        "vid": "19751e06-c798-11e2-a373-000c29833058"
    },
    "details": "No advisory has been released yet.\n\n> Fix NULL pointer dereference in webadmin.\n",
    "id": "FreeBSD-2013-0093",
    "modified": "2013-05-28T00:00:00Z",
    "published": "2013-05-28T00:00:00Z",
    "references": [
        {
            "type": "REPORT",
            "url": "https://github.com/znc/znc/commit/2bd410ee5570cea127233f1133ea22f25174eb28"
        },
        {
            "type": "WEB",
            "url": "https://github.com/znc/znc/commit/2bd410ee5570cea127233f1133ea22f25174eb28"
        }
    ],
    "schema_version": "1.7.0",
    "summary": "znc -- null pointer dereference in webadmin module"
}
