{
    "affected": [
        {
            "package": {
                "ecosystem": "FreeBSD:ports",
                "name": "bitmessage"
            },
            "ranges": [
                {
                    "events": [
                        {
                            "last_affected": "0.6.2"
                        },
                        {
                            "fixed": "0.6.2"
                        },
                        {
                            "introduced": "0"
                        }
                    ],
                    "type": "ECOSYSTEM"
                }
            ]
        }
    ],
    "database_specific": {
        "cite": [
            "https://github.com/Bitmessage/PyBitmessage/releases/tag/v0.6.3"
        ],
        "discovery": "2018-02-13T00:00:00Z",
        "vid": "1a75c84a-11c8-11e8-83e7-485b3931c969"
    },
    "details": "Bitmessage developers report:\n\n> A remote code execution vulnerability has been spotted in use against\n> some users running PyBitmessage v0.6.2. The cause was identified and a\n> fix has been added and released as 0.6.3.2. (Will be updated if/when\n> CVE will be available.)\n",
    "id": "FreeBSD-2018-0043",
    "modified": "2018-02-14T00:00:00Z",
    "published": "2018-02-14T00:00:00Z",
    "references": [
        {
            "type": "REPORT",
            "url": "https://github.com/Bitmessage/PyBitmessage/releases/tag/v0.6.3"
        },
        {
            "type": "WEB",
            "url": "https://github.com/Bitmessage/PyBitmessage/releases/tag/v0.6.3"
        },
        {
            "type": "WEB",
            "url": "https://bitmessage.org/wiki/Main_Page"
        }
    ],
    "schema_version": "1.7.0",
    "summary": "bitmessage -- remote code execution vulnerability"
}
