{
    "affected": [
        {
            "package": {
                "ecosystem": "FreeBSD:ports",
                "name": "wordpress"
            },
            "ranges": [
                {
                    "events": [
                        {
                            "fixed": "5.0.1,1"
                        },
                        {
                            "introduced": "0"
                        }
                    ],
                    "type": "ECOSYSTEM"
                }
            ]
        },
        {
            "package": {
                "ecosystem": "FreeBSD:ports",
                "name": "fr-wordpress"
            },
            "ranges": [
                {
                    "events": [
                        {
                            "fixed": "5.0.1,1"
                        },
                        {
                            "introduced": "0"
                        }
                    ],
                    "type": "ECOSYSTEM"
                }
            ]
        },
        {
            "package": {
                "ecosystem": "FreeBSD:ports",
                "name": "de-wordpress"
            },
            "ranges": [
                {
                    "events": [
                        {
                            "fixed": "5.0.1"
                        },
                        {
                            "introduced": "0"
                        }
                    ],
                    "type": "ECOSYSTEM"
                }
            ]
        },
        {
            "package": {
                "ecosystem": "FreeBSD:ports",
                "name": "zh_CN-wordpress"
            },
            "ranges": [
                {
                    "events": [
                        {
                            "fixed": "5.0.1"
                        },
                        {
                            "introduced": "0"
                        }
                    ],
                    "type": "ECOSYSTEM"
                }
            ]
        },
        {
            "package": {
                "ecosystem": "FreeBSD:ports",
                "name": "zh_TW-wordpress"
            },
            "ranges": [
                {
                    "events": [
                        {
                            "fixed": "5.0.1"
                        },
                        {
                            "introduced": "0"
                        }
                    ],
                    "type": "ECOSYSTEM"
                }
            ]
        },
        {
            "package": {
                "ecosystem": "FreeBSD:ports",
                "name": "ja-wordpress"
            },
            "ranges": [
                {
                    "events": [
                        {
                            "fixed": "5.0.1"
                        },
                        {
                            "introduced": "0"
                        }
                    ],
                    "type": "ECOSYSTEM"
                }
            ]
        },
        {
            "package": {
                "ecosystem": "FreeBSD:ports",
                "name": "ru-wordpress"
            },
            "ranges": [
                {
                    "events": [
                        {
                            "fixed": "5.0.1"
                        },
                        {
                            "introduced": "0"
                        }
                    ],
                    "type": "ECOSYSTEM"
                }
            ]
        }
    ],
    "database_specific": {
        "cite": [
            "https://wordpress.org/news/2018/12/wordpress-5-0-1-security-release/"
        ],
        "discovery": "2018-12-13T00:00:00Z",
        "vid": "4b98613c-0078-11e9-b05b-00e04c1ea73d"
    },
    "details": "wordpress developers reports:\n\n> WordPress versions 5.0 and earlier are affected by the following bugs,\n> which are fixed in version 5.0.1. Updated versions of WordPress 4.9\n> and older releases are also available, for users who have not yet\n> updated to 5.0.\n>\n> Karim El Ouerghemmi discovered that authors could alter meta data to\n> delete files that they weren't authorized to.\n>\n> Simon Scannell of RIPS Technologies discovered that authors could\n> create posts of unauthorized post types with specially crafted input.\n>\n> Sam Thomas discovered that contributors could craft meta data in a way\n> that resulted in PHP object injection.\n>\n> Tim Coen discovered that contributors could edit new comments from\n> higher-privileged users, potentially leading to a cross-site scripting\n> vulnerability.\n>\n> Tim Coen also discovered that specially crafted URL inputs could lead\n> to a cross-site scripting vulnerability in some circumstances.\n> WordPress itself was not affected, but plugins could be in some\n> situations.\n>\n> Team Yoast discovered that the user activation screen could be indexed\n> by search engines in some uncommon configurations, leading to exposure\n> of email addresses, and in some rare cases, default generated\n> passwords.\n>\n> Tim Coen and Slavco discovered that authors on Apache-hosted sites\n> could upload specifically crafted files that bypass MIME verification,\n> leading to a cross-site scripting vulnerability.\n",
    "id": "FreeBSD-2018-0302",
    "modified": "2018-12-15T00:00:00Z",
    "published": "2018-12-15T00:00:00Z",
    "references": [
        {
            "type": "REPORT",
            "url": "https://wordpress.org/news/2018/12/wordpress-5-0-1-security-release/"
        },
        {
            "type": "WEB",
            "url": "https://wordpress.org/news/2018/12/wordpress-5-0-1-security-release/"
        }
    ],
    "schema_version": "1.7.0",
    "summary": "wordpress -- multiple issues"
}
