{
    "affected": [
        {
            "package": {
                "ecosystem": "FreeBSD:ports",
                "name": "p5-DBI-137"
            },
            "ranges": [
                {
                    "events": [
                        {
                            "introduced": "0"
                        }
                    ],
                    "type": "ECOSYSTEM"
                }
            ]
        },
        {
            "package": {
                "ecosystem": "FreeBSD:ports",
                "name": "p5-DBI"
            },
            "ranges": [
                {
                    "events": [
                        {
                            "fixed": "1.37_1"
                        },
                        {
                            "introduced": "0"
                        }
                    ],
                    "type": "ECOSYSTEM"
                },
                {
                    "events": [
                        {
                            "introduced": "1.38"
                        },
                        {
                            "fixed": "1.48"
                        }
                    ],
                    "type": "ECOSYSTEM"
                }
            ]
        }
    ],
    "database_specific": {
        "discovery": "2005-01-25T00:00:00Z",
        "vid": "8cfb6f42-d2b0-11da-a672-000e0c2e438a"
    },
    "details": "Javier Fern\u00e1ndez-Sanguino Pe\u00f1a reports:\n\n> The DBI library, the Perl5 database interface, creates a\n> temporary PID file in an insecure manner. This can be\n> exploited by a malicious user to overwrite arbitrary files\n> owned by the person executing the parts of the library.",
    "id": "FreeBSD-kernel-2006-0148",
    "modified": "2006-05-11T00:00:00Z",
    "published": "2006-04-23T00:00:00Z",
    "references": [
        {
            "type": "ADVISORY",
            "url": "https://www.securityfocus.com/bid/12360/info"
        },
        {
            "type": "ADVISORY",
            "url": "https://api.osv.dev/v1/vulns/CAN-2005-0077"
        },
        {
            "type": "WEB",
            "url": "http://www.debian.org/security/2005/dsa-658"
        }
    ],
    "schema_version": "1.7.0",
    "summary": "p5-DBI -- insecure temporary file creation vulnerability"
}
