{
    "affected": [
        {
            "package": {
                "ecosystem": "FreeBSD:ports",
                "name": "openvpn"
            },
            "ranges": [
                {
                    "events": [
                        {
                            "fixed": "2.3.11"
                        },
                        {
                            "introduced": "0"
                        }
                    ],
                    "type": "ECOSYSTEM"
                }
            ]
        },
        {
            "package": {
                "ecosystem": "FreeBSD:ports",
                "name": "openvpn-polarssl"
            },
            "ranges": [
                {
                    "events": [
                        {
                            "fixed": "2.3.11"
                        },
                        {
                            "introduced": "0"
                        }
                    ],
                    "type": "ECOSYSTEM"
                }
            ]
        }
    ],
    "database_specific": {
        "cite": [
            "https://sourceforge.net/p/openvpn/mailman/message/35076507/"
        ],
        "discovery": "2016-03-03T00:00:00Z",
        "vid": "0dc8be9e-19af-11e6-8de0-080027ef73ec"
    },
    "details": "Samuli Sepp\u00e4nen reports:\n\n> OpenVPN 2.3.11 \\[\\...\\] fixes two vulnerabilities: a port-share bug\n> with DoS potential and a buffer overflow by user supplied data when\n> using pam authentication.\\[\\...\\]\n",
    "id": "FreeBSD-2016-0210",
    "modified": "2016-05-14T00:00:00Z",
    "published": "2016-05-14T00:00:00Z",
    "references": [
        {
            "type": "REPORT",
            "url": "https://sourceforge.net/p/openvpn/mailman/message/35076507/"
        },
        {
            "type": "WEB",
            "url": "https://sourceforge.net/p/openvpn/mailman/message/35076507/"
        },
        {
            "type": "WEB",
            "url": "https://community.openvpn.net/openvpn/wiki/ChangesInOpenvpn23#OpenVPN2.3.11"
        }
    ],
    "schema_version": "1.7.0",
    "summary": "OpenVPN -- Buffer overflow in PAM authentication and DoS through port sharing"
}
